{
  "name": "Ubuntu 22.04 Codespace with SSH",
  "image": "ghcr.io/devcontainers/base:ubuntu-22.04",
  "features": {
    "ghcr.io/devcontainers/features/sshd:1": {}
  },
  "runArgs": [
    "--user=root"
  ],
  "settings": {
    "terminal.integrated.shell.linux": "/bin/bash"
  },
  "postCreateCommand": "echo 'root:root' | chpasswd",
  "mounts": [
    "source=${localWorkspaceFolder},target=/workspace,type=bind"
  ],
  "forwardPorts": [22],
  "remoteUser": "root",
  "workspaceMount": "source=${localWorkspaceFolder},target=/workspace,type=bind"
}
